odoo9_addon_pos_product_template-9.0.0.0.2-nspkg.pth
odoo_addons/pos_product_template/__init__.py
odoo_addons/pos_product_template/__openerp__.py
odoo_addons/pos_product_template/demo/product_attribute_value.yml
odoo_addons/pos_product_template/demo/product_product.yml
odoo_addons/pos_product_template/demo/res_groups.yml
odoo_addons/pos_product_template/i18n/es.po
odoo_addons/pos_product_template/i18n/fr.po
odoo_addons/pos_product_template/i18n/pos_product_template.pot
odoo_addons/pos_product_template/static/description/icon.png
odoo_addons/pos_product_template/static/src/css/ppt.css
odoo_addons/pos_product_template/static/src/img/screenshots/pos_product_template.png
odoo_addons/pos_product_template/static/src/js/ppt.js
odoo_addons/pos_product_template/static/src/xml/ppt.xml
odoo_addons/pos_product_template/view/view.xml
odoo9_addon_pos_product_template-9.0.0.0.2.dist-info/METADATA
odoo9_addon_pos_product_template-9.0.0.0.2.dist-info/WHEEL
odoo9_addon_pos_product_template-9.0.0.0.2.dist-info/namespace_packages.txt
odoo9_addon_pos_product_template-9.0.0.0.2.dist-info/top_level.txt
odoo9_addon_pos_product_template-9.0.0.0.2.dist-info/RECORD
